pydevice/__init__.py
pydevice/auth.py
pydevice/connector.py
pydevice/database.py
pydevice/destination.py
pydevice/device.py
pydevice/device_magic.py
pydevice/dispatch.py
pydevice/form.py
pydevice/group.py
pydevice/resource.py
pydevice-0.3.3.dist-info/LICENSE
pydevice-0.3.3.dist-info/METADATA
pydevice-0.3.3.dist-info/WHEEL
pydevice-0.3.3.dist-info/top_level.txt
pydevice-0.3.3.dist-info/RECORD
