Metadata-Version: 2.1
Name: pydevice
Version: 0.3.3
Summary: Device Magic API Wrapper
Home-page: https://github.com/aseli1/pydevice
Author: Anthony Seliga
Author-email: anthony.seliga@gmail.com
License: MIT
Platform: UNKNOWN
Requires-Python: >3.0
Requires-Dist: requests
Requires-Dist: vcrpy
Requires-Dist: pytest
